demo_focus_blocker/blocker.py
demo_focus_blocker/init.py
demo_focus_blocker/tests.py
demo_focus_blocker-0.1.4.dist-info/licenses/LICENSE
demo_focus_blocker-0.1.4.dist-info/METADATA
demo_focus_blocker-0.1.4.dist-info/WHEEL
demo_focus_blocker-0.1.4.dist-info/entry_points.txt
demo_focus_blocker-0.1.4.dist-info/top_level.txt
demo_focus_blocker-0.1.4.dist-info/RECORD
