Metadata-Version: 2.4
Name: demo-focus-blocker
Version: 0.1.4
Summary: A simple Python package to block distracting websites during focus hours
Author-email: Shyam Tyagi <sst@gmail.com>
License: 
Project-URL: Homepage, https://github.com/demo/demo-focus-blocker
Project-URL: Repository, https://github.com/demo/demo-focus-blocker
Project-URL: Bug Reports, https://github.com/demo/demo-focus-blocker/issues
Keywords: productivity,focus,blocker,time-management
Classifier: Development Status :: 3 - Alpha
Classifier: Intended Audience :: Developers
Classifier: License :: OSI Approved :: MIT License
Classifier: Operating System :: OS Independent
Classifier: Programming Language :: Python :: 3
Classifier: Programming Language :: Python :: 3.8
Classifier: Programming Language :: Python :: 3.9
Classifier: Programming Language :: Python :: 3.10
Classifier: Programming Language :: Python :: 3.11
Classifier: Programming Language :: Python :: 3.12
License-File: LICENSE
Provides-Extra: dev
Requires-Dist: pytest; extra == "dev"
Requires-Dist: black; extra == "dev"
Requires-Dist: flake8; extra == "dev"
Dynamic: license-file
